ibmecstats/__init__.py
ibmecstats/utils.py
ibmecstats-0.1.3.dist-info/METADATA
ibmecstats-0.1.3.dist-info/WHEEL
ibmecstats-0.1.3.dist-info/top_level.txt
ibmecstats-0.1.3.dist-info/RECORD
