Metadata-Version: 2.4
Name: ibmecstats
Version: 0.1.3
Summary: Uma biblioteca de estatística para fins acadêmicos do IBMEC.
Author-email: Carlos Eduardo Leal de Castro <lealdecastro@gmail.com>
Project-URL: Homepage, https://github.com/carloselcastro/ibmecstats
Classifier: Programming Language :: Python :: 3
Classifier: License :: OSI Approved :: MIT License
Classifier: Operating System :: OS Independent
Classifier: Intended Audience :: Education
Classifier: Topic :: Scientific/Engineering :: Mathematics
Requires-Python: >=3.11
Requires-Dist: numpy
